{
  "kind": "collectionType",
  "collectionName": "casino_bonuses",
  "info": {
    "singularName": "casino-bonus",
    "pluralName": "casino-bonuses",
    "displayName": "Casino Bonus"
  },
  "options": {
    "draftAndPublish": true
  },
  "pluginOptions": {},
  "attributes": {
    "Name": {
      "type": "string"
    },
    "Logo": {
      "type": "media",
      "multiple": false,
      "allowedTypes": [
        "images",
        "files",
        "videos",
        "audios"
      ]
    },
    "BonusLink": {
      "type": "string"
    },
    "Welcome_pack_text": {
      "type": "string",
      "pluginOptions": {
        "i18n": {
          "localized": true
        }
      }
    },
    "Visit_casino_link": {
      "type": "string",
      "pluginOptions": {
        "i18n": {
          "localized": true
        }
      }
    },
    "What_we_like": {
      "type": "blocks",
      "pluginOptions": {
        "i18n": {
          "localized": true
        }
      }
    },
    "What_we_dont_like": {
      "type": "blocks",
      "pluginOptions": {
        "i18n": {
          "localized": true
        }
      }
    },
    "General_tab": {
      "type": "component",
      "pluginOptions": {
        "i18n": {
          "localized": true
        }
      },
      "component": "page-components.info-block",
      "repeatable": true
    },
    "Payments_tab": {
      "type": "component",
      "pluginOptions": {
        "i18n": {
          "localized": true
        }
      },
      "component": "page-components.info-block",
      "repeatable": true
    },
    "Games_tab": {
      "type": "component",
      "pluginOptions": {
        "i18n": {
          "localized": true
        }
      },
      "component": "page-components.info-block",
      "repeatable": true
    },
    "About_casino": {
      "type": "blocks",
      "pluginOptions": {
        "i18n": {
          "localized": true
        }
      }
    },
    "Rating_Num": {
      "type": "decimal",
      "pluginOptions": {
        "i18n": {
          "localized": true
        }
      },
      "min": 0,
      "max": 10
    },
    "Is_new": {
      "type": "boolean",
      "pluginOptions": {
        "i18n": {
          "localized": true
        }
      }
    }
  }
}
